MANIFEST.in
NEWS.txt
README.rst
setup.py
requirements/develop.txt
src/acidfile/__init__.py
src/acidfile.egg-info/PKG-INFO
src/acidfile.egg-info/SOURCES.txt
src/acidfile.egg-info/dependency_links.txt
src/acidfile.egg-info/not-zip-safe
src/acidfile.egg-info/top_level.txt
tests/features/basic.feature
tests/features/consistency.feature
tests/features/context.feature
tests/features/copies.feature
tests/features/durability.feature
tests/features/extended_file.feature
tests/features/isolation.feature