Metadata-Version: 1.1
Name: acidfile
Version: 1.2.0
Summary: ACID transaction with common files
Home-page: https://github.com/nilp0inter/acidfile
Author: Roberto Abdelkader MartÃ­nez PÃ©rez
Author-email: robertomartinezp@gmail.com
License: GPLv3
Keywords: ACID transactional file
Platform: UNKNOWN
Classifier: Development Status :: 5 - Production/Stable
Classifier: Intended Audience :: Developers
Classifier: License :: OSI Approved :: GNU General Public License v3 (GPLv3)
Classifier: Programming Language :: Python :: 2.6
Classifier: Programming Language :: Python :: 2.7
Classifier: Programming Language :: Python :: 3.2
Classifier: Programming Language :: Python :: 3.3
Classifier: Programming Language :: Python :: Implementation :: PyPy
Classifier: Topic :: Software Development :: Embedded Systems
Classifier: Topic :: System :: Archiving
